fpml_semantic_model/__init__.py
fpml_semantic_model/all_xsd_data.json
fpml_semantic_model/embedding_generator.py
fpml_semantic_model/fpml_semantic_model.py
fpml_semantic_model-0.2.4.dist-info/METADATA
fpml_semantic_model-0.2.4.dist-info/WHEEL
fpml_semantic_model-0.2.4.dist-info/top_level.txt
fpml_semantic_model-0.2.4.dist-info/RECORD
