Metadata-Version: 2.4
Name: fpml-semantic-model
Version: 0.2.4
Summary: A semantic search and structural analysis model for FpML XSD schemas.
Home-page: https://github.com/thelocalhost-in/fpml-semantic-model
Author: thelocalhost-in
Author-email: thelocalhost.in@gmail.com
Keywords: fpml xsd xml finance machine-learning semantic-search
Classifier: Development Status :: 3 - Alpha
Classifier: Intended Audience :: Developers
Classifier: Intended Audience :: Financial and Insurance Industry
Classifier: License :: OSI Approved :: MIT License
Classifier: Programming Language :: Python :: 3
Classifier: Programming Language :: Python :: 3.8
Classifier: Programming Language :: Python :: 3.9
Classifier: Programming Language :: Python :: 3.10
Classifier: Topic :: Text Processing
Classifier: Topic :: Scientific/Engineering :: Information Analysis
Requires-Python: >=3.8
Dynamic: author
Dynamic: author-email
Dynamic: classifier
Dynamic: description-content-type
Dynamic: home-page
Dynamic: keywords
Dynamic: requires-python
Dynamic: summary
